zod/__init__.py
zod/_zod_dataset.py
zod/constants.py
zod/zod_drives.py
zod/zod_frames.py
zod/zod_sequences.py
zod/anno/ego_road.py
zod/anno/lane.py
zod/anno/object.py
zod/anno/parser.py
zod/anno/road_condition.py
zod/anno/tsr/class_map.py
zod/anno/tsr/traffic_sign.py
zod/cli/download.py
zod/cli/extract_tsr_patches.py
zod/cli/generate_coco_json.py
zod/cli/main.py
zod/cli/utils.py
zod/cli/verify.py
zod/cli/visualize_lidar.py
zod/data_classes/__init__.py
zod/data_classes/_serializable.py
zod/data_classes/box.py
zod/data_classes/calibration.py
zod/data_classes/ego_motion.py
zod/data_classes/frame.py
zod/data_classes/geometry.py
zod/data_classes/info.py
zod/data_classes/metadata.py
zod/data_classes/oxts.py
zod/data_classes/sensor.py
zod/data_classes/sequence.py
zod/data_classes/vehicle_data.py
zod/eval/README.md
zod/eval/tsr.py
zod/eval/detection/__init__.py
zod/eval/detection/constants.py
zod/eval/detection/eval_nuscenes_style.py
zod/eval/detection/_experimental/eval.py
zod/eval/detection/_experimental/matching.py
zod/eval/detection/_experimental/utils.py
zod/eval/detection/_nuscenes_eval/LICENCE.txt
zod/eval/detection/_nuscenes_eval/changes.txt
zod/eval/detection/_nuscenes_eval/common/data_classes.py
zod/eval/detection/_nuscenes_eval/common/utils.py
zod/eval/detection/_nuscenes_eval/detection/README.md
zod/eval/detection/_nuscenes_eval/detection/algo.py
zod/eval/detection/_nuscenes_eval/detection/constants.py
zod/eval/detection/_nuscenes_eval/detection/data_classes.py
zod/utils/compensation.py
zod/utils/geometry.py
zod/utils/polygon_transformations.py
zod/utils/utils.py
zod/utils/visualization.py
zod/visualization/bev_utils.py
zod/visualization/colorlabeler.py
zod/visualization/ego_road_visualization.py
zod/visualization/lane_markings_visualization.py
zod/visualization/lidar_3d.py
zod/visualization/lidar_bev.py
zod/visualization/lidar_on_image.py
zod/visualization/object_visualization.py
zod/visualization/oxts_on_image.py
zod/visualization/oxts_visualization.py
zod-0.7.dist-info/METADATA
zod-0.7.dist-info/WHEEL
zod-0.7.dist-info/entry_points.txt
zod-0.7.dist-info/licenses/LICENSE
zod-0.7.dist-info/RECORD
