Metadata-Version: 2.4
Name: zod
Version: 0.7
Summary: Zenseact Open Dataset
Project-URL: Homepage, https://zod.zenseact.com
Project-URL: Repository, https://github.com/zenseact/zod
Author-email: Zenseact <opendataset@zenseact.com>
License-Expression: MIT
License-File: LICENSE
Requires-Python: >=3.9
Requires-Dist: dataclass-wizard!=0.31,!=0.32,>=0.22
Requires-Dist: h5py>=3.1
Requires-Dist: numpy-quaternion>=2022.4.2
Requires-Dist: numpy>=1.19
Requires-Dist: pillow>=7
Requires-Dist: pyquaternion>=0.9
Requires-Dist: scipy>=1.5
Requires-Dist: tqdm>=4.60
Provides-Extra: all
Requires-Dist: dash-bootstrap-components~=1.1; extra == 'all'
Requires-Dist: dropbox>=11.36.0; extra == 'all'
Requires-Dist: imageio<3,>=2; extra == 'all'
Requires-Dist: matplotlib<4,>=3; extra == 'all'
Requires-Dist: notebook>=5; extra == 'all'
Requires-Dist: opencv-python<5,>=4; extra == 'all'
Requires-Dist: pandas~=1.3; extra == 'all'
Requires-Dist: plotly<6,>=5; extra == 'all'
Requires-Dist: typer[all]>=0.15.0; extra == 'all'
Provides-Extra: cli
Requires-Dist: dropbox>=11.36.0; extra == 'cli'
Requires-Dist: typer[all]>=0.15.0; extra == 'cli'
